bme/__init__.py
bme/__version__.py
bme/config.py
bme/config_mng.py
bme/convertor.py
bme/init.py
bme/main.py
bme/tools.py
bme/daemon/__init__.py
bme/daemon/api.py
bme/daemon/daemon.py
bme/historitian/__init__.py
bme/historitian/historitian.py
bme/notifier/__init__.py
bme/notifier/version_notifier.py
bme/saved_types/__init__.py
bme/saved_types/bookmark.py
bme/saved_types/parent_type.py
bme/saved_types/sequence.py
bme-1.4.4.dist-info/LICENSE.md
bme-1.4.4.dist-info/METADATA
bme-1.4.4.dist-info/WHEEL
bme-1.4.4.dist-info/entry_points.txt
bme-1.4.4.dist-info/top_level.txt
bme-1.4.4.dist-info/zip-safe
bme-1.4.4.dist-info/RECORD
