Metadata-Version: 2.1
Name: bme
Version: 1.4.4
Summary: Never use notepads or history for searching for your past commands. With BME you can bookmark your commands, search in your bookmarked commands and execute them with edit possibility before execution. 
Home-page: https://github.com/jiri-otoupal/bme
Author: Jiri Otoupal
Author-email: jiri-otoupal@ips-database.eu
License: MIT
Keywords: Bookmark My Executed Commands
Classifier: Development Status :: 4 - Beta
Classifier: Intended Audience :: Developers
Classifier: Programming Language :: Python :: 3.7
Classifier: Programming Language :: Python :: 3.8
Classifier: Programming Language :: Python :: 3.9
Classifier: Programming Language :: Python :: 3.10
Classifier: Programming Language :: Python :: 3.11
Requires-Python: >=3.7,<4
License-File: LICENSE.md
Requires-Dist: click
Requires-Dist: rich
Requires-Dist: inquirerpy
Requires-Dist: lastversion
Requires-Dist: uvicorn
Requires-Dist: fastapi
Requires-Dist: requests
Requires-Dist: semantic-version
Requires-Dist: escapejson
Requires-Dist: watchdog
Provides-Extra: dev
Requires-Dist: black ==22.* ; extra == 'dev'
